{
  "config": {
    "data_config": {
      "raw_path": "preprocessed/GoEmotions.parquet",
      "cache_path": "preprocessed/GoEmotions-split-cache/",
      "split_names": [
        "train",
        "valid",
        "test"
      ],
      "split_portions": [
        0.8,
        0.1,
        0.1
      ],
      "split_mode": "column",
      "dataset_format": "goemotions",
      "target_column": "emotions_label",
      "text_column": "text"
    },
    "extractor_config": {
      "ex_type": "bert",
      "ex_args": {
        "bert_model": "bert-base-uncased",
        "freeze_output": false,
        "max_length": 25
      }
    },
    "model_config": {
      "model_name": "dnnpool",
      "problem_type": "multilabel",
      "batch_size": 64,
      "model_conf": {
        "hidden_size": 100,
        "num_layers": 1,
        "num_epochs": 60,
        "learning_rate": 0.001,
        "epsilon": 1e-05,
        "activation": "tanh",
        "pool_mode": "attention",
        "optimizer": "adamw"
      }
    },
    "label_names": [
      "admiration",
      "amusement",
      "anger",
      "annoyance",
      "approval",
      "caring",
      "confusion",
      "curiosity",
      "desire",
      "disappointment",
      "disapproval",
      "disgust",
      "embarrassment",
      "excitement",
      "fear",
      "gratitude",
      "grief",
      "joy",
      "love",
      "nervousness",
      "optimism",
      "pride",
      "realization",
      "relief",
      "remorse",
      "sadness",
      "surprise",
      "neutral"
    ],
    "seed": 123,
    "output_path": "output/GoEmotions/neural/",
    "model_path": null
  },
  "results": {
    "train": {
      "labels": {
        "admiration": {
          "precision": 0.6902912621359223,
          "recall": 0.6886198547215496,
          "f1": 0.6894545454545454,
          "support": 4130.0
        },
        "amusement": {
          "precision": 0.7437165224557066,
          "recall": 0.7753436426116839,
          "f1": 0.7592008412197686,
          "support": 2328.0
        },
        "anger": {
          "precision": 0.5172626387176326,
          "recall": 0.5354179961710275,
          "f1": 0.526183756663531,
          "support": 1567.0
        },
        "annoyance": {
          "precision": 0.29894301470588236,
          "recall": 0.5267206477732793,
          "f1": 0.3814130753444737,
          "support": 2470.0
        },
        "approval": {
          "precision": 0.3702090592334495,
          "recall": 0.4338210275603947,
          "f1": 0.39949866833777226,
          "support": 2939.0
        },
        "caring": {
          "precision": 0.4268802228412256,
          "recall": 0.5639374425022999,
          "f1": 0.48592944906856916,
          "support": 1087.0
        },
        "confusion": {
          "precision": 0.4739099356683345,
          "recall": 0.48464912280701755,
          "f1": 0.4792193711601012,
          "support": 1368.0
        },
        "curiosity": {
          "precision": 0.49612403100775193,
          "recall": 0.730260155180283,
          "f1": 0.5908419497784343,
          "support": 2191.0
        },
        "desire": {
          "precision": 0.576271186440678,
          "recall": 0.5834633385335414,
          "f1": 0.57984496124031,
          "support": 641.0
        },
        "disappointment": {
          "precision": 0.362012987012987,
          "recall": 0.35145784081954295,
          "f1": 0.35665733706517394,
          "support": 1269.0
        },
        "disapproval": {
          "precision": 0.35513385293120975,
          "recall": 0.5182987141444114,
          "f1": 0.42147597023929223,
          "support": 2022.0
        },
        "disgust": {
          "precision": 0.5346820809248555,
          "recall": 0.4665825977301387,
          "f1": 0.4983164983164983,
          "support": 793.0
        },
        "embarrassment": {
          "precision": 0.6887966804979253,
          "recall": 0.5478547854785478,
          "f1": 0.6102941176470589,
          "support": 303.0
        },
        "excitement": {
          "precision": 0.4423459244532803,
          "recall": 0.5216881594372802,
          "f1": 0.47875201721355565,
          "support": 853.0
        },
        "fear": {
          "precision": 0.7034596375617792,
          "recall": 0.7164429530201343,
          "f1": 0.709891936824605,
          "support": 596.0
        },
        "gratitude": {
          "precision": 0.9321681231793592,
          "recall": 0.8414725770097671,
          "f1": 0.8845014807502468,
          "support": 2662.0
        },
        "grief": {
          "precision": 0.8115942028985508,
          "recall": 0.7272727272727273,
          "f1": 0.767123287671233,
          "support": 77.0
        },
        "joy": {
          "precision": 0.586940572267058,
          "recall": 0.5509641873278237,
          "f1": 0.5683836589698047,
          "support": 1452.0
        },
        "love": {
          "precision": 0.7763334827431645,
          "recall": 0.8302972195589645,
          "f1": 0.8024090803798934,
          "support": 2086.0
        },
        "nervousness": {
          "precision": 0.7301587301587301,
          "recall": 0.5609756097560976,
          "f1": 0.6344827586206897,
          "support": 164.0
        },
        "optimism": {
          "precision": 0.6451612903225806,
          "recall": 0.5186590765338394,
          "f1": 0.5750350631136044,
          "support": 1581.0
        },
        "pride": {
          "precision": 0.8505747126436781,
          "recall": 0.6666666666666666,
          "f1": 0.7474747474747474,
          "support": 111.0
        },
        "realization": {
          "precision": 0.3293135435992579,
          "recall": 0.31981981981981983,
          "f1": 0.32449725776965266,
          "support": 1110.0
        },
        "relief": {
          "precision": 0.75,
          "recall": 0.5294117647058824,
          "f1": 0.6206896551724139,
          "support": 153.0
        },
        "remorse": {
          "precision": 0.6821963394342762,
          "recall": 0.7522935779816514,
          "f1": 0.7155322862129145,
          "support": 545.0
        },
        "sadness": {
          "precision": 0.5763665594855305,
          "recall": 0.5407239819004525,
          "f1": 0.5579766536964981,
          "support": 1326.0
        },
        "surprise": {
          "precision": 0.6485355648535565,
          "recall": 0.5849056603773585,
          "f1": 0.6150793650793651,
          "support": 1060.0
        },
        "neutral": {
          "precision": 0.5818115979514769,
          "recall": 0.790983894788663,
          "f1": 0.670461997019374,
          "support": 14219.0
        }
      },
      "macro_f1": 0.5875222066965761,
      "micro_f1": 0.604683720522416
    },
    "valid": {
      "labels": {
        "admiration": {
          "precision": 0.6859504132231405,
          "recall": 0.680327868852459,
          "f1": 0.6831275720164609,
          "support": 488.0
        },
        "amusement": {
          "precision": 0.6809815950920245,
          "recall": 0.7326732673267327,
          "f1": 0.7058823529411765,
          "support": 303.0
        },
        "anger": {
          "precision": 0.34951456310679613,
          "recall": 0.5538461538461539,
          "f1": 0.42857142857142855,
          "support": 195.0
        },
        "annoyance": {
          "precision": 0.24362606232294617,
          "recall": 0.5676567656765676,
          "f1": 0.3409316154608523,
          "support": 303.0
        },
        "approval": {
          "precision": 0.3917525773195876,
          "recall": 0.2871536523929471,
          "f1": 0.3313953488372093,
          "support": 397.0
        },
        "caring": {
          "precision": 0.46206896551724136,
          "recall": 0.43790849673202614,
          "f1": 0.4496644295302013,
          "support": 153.0
        },
        "confusion": {
          "precision": 0.2724014336917563,
          "recall": 0.5,
          "f1": 0.3526682134570766,
          "support": 152.0
        },
        "curiosity": {
          "precision": 0.3786848072562358,
          "recall": 0.6733870967741935,
          "f1": 0.4847605224963715,
          "support": 248.0
        },
        "desire": {
          "precision": 0.5576923076923077,
          "recall": 0.37662337662337664,
          "f1": 0.4496124031007752,
          "support": 77.0
        },
        "disappointment": {
          "precision": 0.27403846153846156,
          "recall": 0.3496932515337423,
          "f1": 0.30727762803234504,
          "support": 163.0
        },
        "disapproval": {
          "precision": 0.2845849802371542,
          "recall": 0.4931506849315068,
          "f1": 0.3609022556390977,
          "support": 292.0
        },
        "disgust": {
          "precision": 0.3652173913043478,
          "recall": 0.4329896907216495,
          "f1": 0.3962264150943396,
          "support": 97.0
        },
        "embarrassment": {
          "precision": 0.6875,
          "recall": 0.3142857142857143,
          "f1": 0.43137254901960786,
          "support": 35.0
        },
        "excitement": {
          "precision": 0.2916666666666667,
          "recall": 0.3645833333333333,
          "f1": 0.32407407407407407,
          "support": 96.0
        },
        "fear": {
          "precision": 0.640625,
          "recall": 0.45555555555555555,
          "f1": 0.5324675324675325,
          "support": 90.0
        },
        "gratitude": {
          "precision": 0.930379746835443,
          "recall": 0.8212290502793296,
          "f1": 0.8724035608308606,
          "support": 358.0
        },
        "grief": {
          "precision": 0.5,
          "recall": 0.23076923076923078,
          "f1": 0.3157894736842105,
          "support": 13.0
        },
        "joy": {
          "precision": 0.562962962962963,
          "recall": 0.4418604651162791,
          "f1": 0.49511400651465803,
          "support": 172.0
        },
        "love": {
          "precision": 0.6879194630872483,
          "recall": 0.8134920634920635,
          "f1": 0.7454545454545454,
          "support": 252.0
        },
        "nervousness": {
          "precision": 0.2857142857142857,
          "recall": 0.2857142857142857,
          "f1": 0.2857142857142857,
          "support": 21.0
        },
        "optimism": {
          "precision": 0.5934065934065934,
          "recall": 0.5167464114832536,
          "f1": 0.5524296675191815,
          "support": 209.0
        },
        "pride": {
          "precision": 0.8,
          "recall": 0.26666666666666666,
          "f1": 0.4,
          "support": 15.0
        },
        "realization": {
          "precision": 0.24691358024691357,
          "recall": 0.15748031496062992,
          "f1": 0.1923076923076923,
          "support": 127.0
        },
        "relief": {
          "precision": 0.13636363636363635,
          "recall": 0.16666666666666666,
          "f1": 0.15,
          "support": 18.0
        },
        "remorse": {
          "precision": 0.6301369863013698,
          "recall": 0.6764705882352942,
          "f1": 0.652482269503546,
          "support": 68.0
        },
        "sadness": {
          "precision": 0.4785714285714286,
          "recall": 0.46853146853146854,
          "f1": 0.47349823321554774,
          "support": 143.0
        },
        "surprise": {
          "precision": 0.5660377358490566,
          "recall": 0.46511627906976744,
          "f1": 0.5106382978723404,
          "support": 129.0
        },
        "neutral": {
          "precision": 0.5423728813559322,
          "recall": 0.8154020385050963,
          "f1": 0.651436326622936,
          "support": 1766.0
        }
      },
      "macro_f1": 0.45986438214208397,
      "micro_f1": 0.5491183178374164
    },
    "test": {
      "labels": {
        "admiration": {
          "precision": 0.6674107142857143,
          "recall": 0.5932539682539683,
          "f1": 0.6281512605042017,
          "support": 504.0
        },
        "amusement": {
          "precision": 0.7764705882352941,
          "recall": 0.75,
          "f1": 0.7630057803468209,
          "support": 264.0
        },
        "anger": {
          "precision": 0.45454545454545453,
          "recall": 0.35353535353535354,
          "f1": 0.3977272727272727,
          "support": 198.0
        },
        "annoyance": {
          "precision": 0.22720897615708274,
          "recall": 0.50625,
          "f1": 0.31364956437560504,
          "support": 320.0
        },
        "approval": {
          "precision": 0.32119914346895073,
          "recall": 0.42735042735042733,
          "f1": 0.3667481662591687,
          "support": 351.0
        },
        "caring": {
          "precision": 0.3563218390804598,
          "recall": 0.45925925925925926,
          "f1": 0.401294498381877,
          "support": 135.0
        },
        "confusion": {
          "precision": 0.31225296442687744,
          "recall": 0.5163398692810458,
          "f1": 0.3891625615763547,
          "support": 153.0
        },
        "curiosity": {
          "precision": 0.42424242424242425,
          "recall": 0.6901408450704225,
          "f1": 0.5254691689008043,
          "support": 284.0
        },
        "desire": {
          "precision": 0.5217391304347826,
          "recall": 0.43373493975903615,
          "f1": 0.4736842105263158,
          "support": 83.0
        },
        "disappointment": {
          "precision": 0.13895216400911162,
          "recall": 0.40397350993377484,
          "f1": 0.20677966101694914,
          "support": 151.0
        },
        "disapproval": {
          "precision": 0.2863741339491917,
          "recall": 0.46441947565543074,
          "f1": 0.3542857142857143,
          "support": 267.0
        },
        "disgust": {
          "precision": 0.4752475247524752,
          "recall": 0.3902439024390244,
          "f1": 0.42857142857142855,
          "support": 123.0
        },
        "embarrassment": {
          "precision": 0.6,
          "recall": 0.24324324324324326,
          "f1": 0.34615384615384615,
          "support": 37.0
        },
        "excitement": {
          "precision": 0.6111111111111112,
          "recall": 0.32038834951456313,
          "f1": 0.42038216560509556,
          "support": 103.0
        },
        "fear": {
          "precision": 0.6865671641791045,
          "recall": 0.5897435897435898,
          "f1": 0.6344827586206897,
          "support": 78.0
        },
        "gratitude": {
          "precision": 0.9381107491856677,
          "recall": 0.8181818181818182,
          "f1": 0.874051593323217,
          "support": 352.0
        },
        "grief": {
          "precision": 0.0,
          "recall": 0.0,
          "f1": 0.0,
          "support": 6.0
        },
        "joy": {
          "precision": 0.6029411764705882,
          "recall": 0.5093167701863354,
          "f1": 0.5521885521885521,
          "support": 161.0
        },
        "love": {
          "precision": 0.7241379310344828,
          "recall": 0.7941176470588235,
          "f1": 0.7575150300601203,
          "support": 238.0
        },
        "nervousness": {
          "precision": 0.19230769230769232,
          "recall": 0.21739130434782608,
          "f1": 0.20408163265306123,
          "support": 23.0
        },
        "optimism": {
          "precision": 0.6296296296296297,
          "recall": 0.45698924731182794,
          "f1": 0.529595015576324,
          "support": 186.0
        },
        "pride": {
          "precision": 0.8,
          "recall": 0.25,
          "f1": 0.38095238095238093,
          "support": 16.0
        },
        "realization": {
          "precision": 0.21929824561403508,
          "recall": 0.1724137931034483,
          "f1": 0.19305019305019303,
          "support": 145.0
        },
        "relief": {
          "precision": 0.3333333333333333,
          "recall": 0.18181818181818182,
          "f1": 0.23529411764705885,
          "support": 11.0
        },
        "remorse": {
          "precision": 0.527027027027027,
          "recall": 0.6964285714285714,
          "f1": 0.5999999999999999,
          "support": 56.0
        },
        "sadness": {
          "precision": 0.47096774193548385,
          "recall": 0.46794871794871795,
          "f1": 0.46945337620578775,
          "support": 156.0
        },
        "surprise": {
          "precision": 0.4965034965034965,
          "recall": 0.5035460992907801,
          "f1": 0.5,
          "support": 141.0
        },
        "neutral": {
          "precision": 0.5541890853189854,
          "recall": 0.8069390039171797,
          "f1": 0.6570972886762361,
          "support": 1787.0
        }
      },
      "macro_f1": 0.4501009727923241,
      "micro_f1": 0.5499386759322918
    },
    "thresholds": [
      [
        0.2798110842704773,
        0.18789374828338623,
        0.23677024245262146,
        0.1623571664094925,
        0.183236762881279,
        0.13796159625053406,
        0.22483214735984802,
        0.21994537115097046,
        0.17899182438850403,
        0.21908420324325562,
        0.17066799104213715,
        0.24615991115570068,
        0.18182867765426636,
        0.21211211383342743,
        0.25264647603034973,
        0.38697296380996704,
        0.3182104825973511,
        0.26015979051589966,
        0.26066115498542786,
        0.1734161674976349,
        0.27739405632019043,
        0.3684830367565155,
        0.18523050844669342,
        0.25406911969184875,
        0.22483186423778534,
        0.23207099735736847,
        0.36313602328300476,
        0.33154329657554626
      ],
      [
        0.31562188267707825,
        0.13845294713974,
        0.14544492959976196,
        0.12809020280838013,
        0.22542624175548553,
        0.15557417273521423,
        0.12013110518455505,
        0.14264899492263794,
        0.4018498659133911,
        0.16817039251327515,
        0.13402889668941498,
        0.19481536746025085,
        0.39017224311828613,
        0.21754349768161774,
        0.32742947340011597,
        0.40519407391548157,
        0.4227827191352844,
        0.2937547564506531,
        0.25437286496162415,
        0.12165425717830658,
        0.21111607551574707,
        0.4944925904273987,
        0.24853214621543884,
        0.14231009781360626,
        0.138718843460083,
        0.2572935223579407,
        0.41933804750442505,
        0.2941123843193054
      ],
      [
        0.3418179750442505,
        0.22044357657432556,
        0.2975247800350189,
        0.13199922442436218,
        0.18195205926895142,
        0.1340971440076828,
        0.16270142793655396,
        0.16652743518352509,
        0.1888180524110794,
        0.09538151323795319,
        0.15280276536941528,
        0.2081897109746933,
        0.4007651209831238,
        0.45046576857566833,
        0.2584365904331207,
        0.5140814185142517,
        0.6019139289855957,
        0.32891079783439636,
        0.1938660442829132,
        0.08535407483577728,
        0.31872472167015076,
        0.9635390043258667,
        0.2023829072713852,
        0.38271263241767883,
        0.1948728710412979,
        0.2272356152534485,
        0.23530510067939758,
        0.30687570571899414
      ]
    ]
  }
}